Metadata-Version: 2.1
Name: mypackscal
Version: 0.0.1
Summary: this is a trial package used for calculation.
Home-page: UNKNOWN
Author: Shreyas MR
Author-email: shreyasmr13@gmail.com
License: MIT
Platform: UNKNOWN
License-File: LICENCE.txt
